odoo9_addon_website_anchor_smooth_scroll-9.0.1.0.0.99.dev5-py2.7-nspkg.pth
odoo9_addon_website_anchor_smooth_scroll-9.0.1.0.0.99.dev5.dist-info/DESCRIPTION.rst
odoo9_addon_website_anchor_smooth_scroll-9.0.1.0.0.99.dev5.dist-info/METADATA
odoo9_addon_website_anchor_smooth_scroll-9.0.1.0.0.99.dev5.dist-info/RECORD
odoo9_addon_website_anchor_smooth_scroll-9.0.1.0.0.99.dev5.dist-info/WHEEL
odoo9_addon_website_anchor_smooth_scroll-9.0.1.0.0.99.dev5.dist-info/metadata.json
odoo9_addon_website_anchor_smooth_scroll-9.0.1.0.0.99.dev5.dist-info/namespace_packages.txt
odoo9_addon_website_anchor_smooth_scroll-9.0.1.0.0.99.dev5.dist-info/top_level.txt
odoo_addons/website_anchor_smooth_scroll/README.rst
odoo_addons/website_anchor_smooth_scroll/__init__.py
odoo_addons/website_anchor_smooth_scroll/__openerp__.py
odoo_addons/website_anchor_smooth_scroll/demo/website_anchor_smooth_scroll.xml
odoo_addons/website_anchor_smooth_scroll/i18n/bg.po
odoo_addons/website_anchor_smooth_scroll/i18n/de.po
odoo_addons/website_anchor_smooth_scroll/i18n/es.po
odoo_addons/website_anchor_smooth_scroll/i18n/fr.po
odoo_addons/website_anchor_smooth_scroll/i18n/it.po
odoo_addons/website_anchor_smooth_scroll/i18n/pt_BR.po
odoo_addons/website_anchor_smooth_scroll/i18n/sl.po
odoo_addons/website_anchor_smooth_scroll/i18n/website_anchor_smooth_scroll.pot
odoo_addons/website_anchor_smooth_scroll/static/description/icon.png
odoo_addons/website_anchor_smooth_scroll/static/src/js/website_anchor_smooth_scroll.js
odoo_addons/website_anchor_smooth_scroll/views/website_anchor_smooth_scroll.xml
