Metadata-Version: 2.0
Name: odoo9-addon-website-anchor-smooth-scroll
Version: 9.0.1.0.0.99.dev5
Summary: Replace default behavior for internal links (anchor only) with smooth scroll
Home-page: http://www.antiun.com
Author: Antiun Ingeniería S.L., Tecnativa, LasLabs, Odoo Community Association (OCA)
Author-email: support@odoo-community.org
License: AGPL-3
Platform: UNKNOWN
Classifier: Programming Language :: Python
Classifier: Framework :: Odoo
Classifier: License :: OSI Approved :: GNU Affero General Public License v3
Requires-Python: ~=2.7
Requires-Dist: odoo (<9.1a,>=9.0a)
